wabach/__init__.py
wabach/tensors.py
WaBach-0.1.4.dist-info/LICENSE
WaBach-0.1.4.dist-info/METADATA
WaBach-0.1.4.dist-info/WHEEL
WaBach-0.1.4.dist-info/top_level.txt
WaBach-0.1.4.dist-info/RECORD
